{
  "id": "68b9e9ee-29a5-45a8-bc4d-992b940a2606",
  "platform": "meta",
  "meta_ad_id": "120212787222440548",
  "ad_name": "20240708_BigStop_v01",
  "campaign_name": "[Testing] GY 1 | JotPsych | Prospecting | Sales",
  "campaign_status": "PAUSED",
  "adset_name": "Motion | USA | M-F | 22-65+ | Narrow Targeting [July Batch 1]",
  "headline": "10 days. Unlimited notes. Start your Free Trial today.",
  "body": "There's a new way to spend 50% less time charting.",
  "cta_type": "LEARN_MORE",
  "image_url": null,
  "thumbnail_url": "https://scontent-sjc3-1.xx.fbcdn.net/v/t45.1600-4/566420382_31831677653142197_9067684876757865187_n.png?_nc_cat=105&ccb=1-7&_nc_ohc=3Icji3Sft7AQ7kNvwGtgsKi&_nc_oc=AdpcezSYf0ltopOtFTiAeRuF96ZVoCKIDzeu9xgXxkJZSm44YKbGXxwm16yPgf9g1CjUzGlmg_kx3zxhDoj-DKrx&_nc_zt=1&_nc_ht=scontent-sjc3-1.xx&edm=AAwGEdEEAAAA&_nc_gid=3k3zikfVqm-77Jz5ScY3-w&_nc_tpa=Q5bMBQHp1lcYUilEcQmACayYR_fdPljJxvVHHCHKvDwdJ0johnzppfPbNCDc7DGxgYS4cYGqd0X9P4liFQ&stp=c0.5000x0.5000f_dst-emg0_p64x64_q75_tt6&ur=52f3c4&_nc_sid=58080a&oh=00_AfyxMsoyjeFl7HGfhfqaflwvsJA644IoG_tYo2tMl35Rkg&oe=69CAB206",
  "creative_type": "image",
  "spend": 25.9,
  "impressions": 2477,
  "reach": 2401,
  "clicks": 10,
  "ctr": 0.403714,
  "cpc": 2.59,
  "conversions": 0,
  "cost_per_conversion": null,
  "landing_page_views": 0,
  "video_views": 0,
  "taxonomy": {
    "message_type": "urgency",
    "hook_type": "direct_benefit",
    "cta_type": "learn_more",
    "tone": "urgent",
    "visual_style": "text_heavy",
    "subject_matter": "conceptual",
    "color_mood": "high_contrast",
    "text_density": "headline_subhead",
    "format": "single_image",
    "platform": "meta",
    "placement": "feed",
    "headline_word_count": 9,
    "uses_number": true,
    "uses_question": false,
    "uses_first_person": false,
    "uses_social_proof": false,
    "copy_reading_level": 6.5
  },
  "analyzed_at": "2026-03-26T08:01:30.321580"
}