{
  "id": "6e4e20e4-7d79-40a4-ade6-1a9d355a8928",
  "platform": "meta",
  "meta_ad_id": "120241807175460548",
  "ad_name": "Test: AI for Progress Notes v2",
  "campaign_name": "Test - Instant Forms",
  "campaign_status": "PAUSED",
  "adset_name": "Test: AI for Progress Notes v2",
  "headline": "The AI Scribe You’ve Been Searching for—JotPsych is Built for Behavioral Health",
  "body": "Your practice deserves modern tools. Jotpsych uses AI to create accurate, psychiatry-specific notes in seconds—without the hassle.",
  "cta_type": "LEARN_MORE",
  "image_url": null,
  "thumbnail_url": "https://scontent-sjc3-1.xx.fbcdn.net/v/t15.13418-10/501092416_4141084766152307_6157178853442155690_n.jpg?_nc_cat=103&ccb=1-7&_nc_ohc=oDQOaAmxbDIQ7kNvwFjxRSU&_nc_oc=AdrtP7N6nO24xYq7lIXjdmbvvjmT0XBEdifVHE40WEN3F6QBTAZy4JfjZ2Uu6Ap16oZJ0AuPV1-VZJHfl6kTqYuT&_nc_zt=23&_nc_ht=scontent-sjc3-1.xx&edm=AAwGEdEEAAAA&_nc_gid=aOhqk-sH28XkwnNxpBrKnw&_nc_tpa=Q5bMBQFTSPgi4O7fXjX-qZ8DM0D_Fp882ZAj9o5v6QjpbhudWUAsSJ4jDdgKsj6gUoj3yPWSDnXCN0H4Hw&stp=c0.5000x0.5000f_dst-emg0_p64x64_q75_tt6&ur=c3b633&_nc_sid=58080a&oh=00_AfywYBmjUb7jo6Y_vIMUy02ryR3C3raqB_wW_TYn86rXww&oe=69CAC29E",
  "creative_type": "image",
  "spend": 1920.95,
  "impressions": 58286,
  "reach": 13467,
  "clicks": 506,
  "ctr": 0.868133,
  "cpc": 3.796344,
  "conversions": 38,
  "cost_per_conversion": 50.551316,
  "landing_page_views": 0,
  "video_views": 0,
  "taxonomy": {
    "message_type": "value_prop",
    "hook_type": "direct_benefit",
    "cta_type": "learn_more",
    "tone": "clinical",
    "visual_style": "text_heavy",
    "subject_matter": "conceptual",
    "color_mood": "brand_primary",
    "text_density": "headline_only",
    "format": "single_image",
    "platform": "meta",
    "placement": "feed",
    "headline_word_count": 0,
    "uses_number": false,
    "uses_question": false,
    "uses_first_person": false,
    "uses_social_proof": false,
    "copy_reading_level": 0.0
  },
  "analyzed_at": "2026-03-26T07:45:53.822472"
}